{
  "heroes": [
    {
      "name": "qwerty",
      "description": "asfsdsdfsd",
      "element": "wind",
      "id": 1
    },
    {
      "name": "English",
      "description": "123213",
      "element": "fire",
      "id": 4
    },
    {
      "name": "ashot",
      "description": "fdgdfg",
      "element": "fire",
      "id": 5
    }
  ],
  "filters": [
    {
      "name": "all",
      "label": "Все",
      "className": "btn btn-outline-dark"
    },
    {
      "name": "fire",
      "label": "Огонь",
      "className": "btn btn-danger"
    },
    {
      "name": "water",
      "label": "Вода",
      "className": "btn btn-primary"
    },
    {
      "name": "wind",
      "label": "Ветер",
      "className": "btn btn-success"
    },
    {
      "name": "earth",
      "label": "Земля",
      "className": "btn btn-secondary"
    }
  ]
}